mongomapper/__init__.py
mongomapper/base.py
mongomapper/config.py
mongomapper/encoders.py
mongomapper/errors.py
mongomapper/query.py
mongomapper/reference.py
mongomapper/utils.py
mongomapper-1.2.1.dist-info/LICENSE
mongomapper-1.2.1.dist-info/METADATA
mongomapper-1.2.1.dist-info/WHEEL
mongomapper-1.2.1.dist-info/top_level.txt
mongomapper-1.2.1.dist-info/RECORD
