Metadata-Version: 2.1
Name: mongomapper
Version: 1.2.1
Summary: Mongo ODM for Python
Home-page: https://github.com/fecabrera/mongomapper
Author: Felipe Cabrera
Author-email: fecabrera@protonmail.com
License: MIT
Project-URL: Bug Tracker, https://github.com/fecabrera/mongomapper/issues
Platform: UNKNOWN
Classifier: Programming Language :: Python :: 3
Classifier: License :: OSI Approved :: MIT License
Classifier: Operating System :: OS Independent
Requires-Python: >=3.9
License-File: LICENSE
Requires-Dist: python-dotenv
Requires-Dist: pydantic
Requires-Dist: pymongo[srv]
